seeed_mlx9064x.py
seeed_python_mlx9064x-1.1.4.dist-info/LICENSE
seeed_python_mlx9064x-1.1.4.dist-info/METADATA
seeed_python_mlx9064x-1.1.4.dist-info/WHEEL
seeed_python_mlx9064x-1.1.4.dist-info/top_level.txt
seeed_python_mlx9064x-1.1.4.dist-info/RECORD
